{
  "weights": [
    {
      "date": "2026-02-26",
      "kg": 90.861
    },
    {
      "date": "2026-03-10",
      "kg": 90.345
    },
    {
      "date": "2026-03-12",
      "kg": 88.701
    }
  ],
  "food": [
    {
      "date": "2026-02-28",
      "meal": "lunch",
      "text": "Starbucks coffee (triple shot) with whipped cream, about half a cup."
    }
  ],
  "swims": [
    {
      "date": "2026-03-04",
      "activity_id": 0
    },
    {
      "date": "2026-03-06",
      "activity_id": 0
    },
    {
      "date": "2026-03-09",
      "activity_id": 0
    }
  ],
  "runs": [],
  "strava_token_cache": {
    "access_token": "4139c3bd8e1ad9d55992e025f405fd4143bbf63c",
    "refresh_token": "fe5b9ec763c0462c91c7477e33318c13465ecd2e",
    "expires_at": 1773582701
  },
  "withings_token_cache": {
    "access_token": "ba297cd1330ef4d29b7e179cac1c534e938d4ef9",
    "refresh_token": "be55785369ff7e0e6c7222df20f4fa2d199d2c69",
    "expires_at": 1773586302
  }
}